mantarix_cli/__pyinstaller/__init__.py
mantarix_cli/__pyinstaller/config.py
mantarix_cli/__pyinstaller/hook-mantarix.py
mantarix_cli/__pyinstaller/macos_utils.py
mantarix_cli/__pyinstaller/rthooks/pyi_rth_localhost_mantarixd.py
mantarix_cli/__pyinstaller/rthooks.dat
mantarix_cli/__pyinstaller/utils.py
mantarix_cli/__pyinstaller/win_utils.py
mantarix_cli/cli.py
mantarix_cli/commands/base.py
mantarix_cli/commands/build.py
mantarix_cli/commands/create.py
mantarix_cli/commands/options.py
mantarix_cli/commands/pack.py
mantarix_cli/commands/publish.py
mantarix_cli/commands/run.py
mantarix_cli/utils/merge.py
mantarix_cli/utils/project_dependencies.py
mantarix_cli/utils/pyproject_toml.py
mantarix_cli/version.py
mantarix_cli-1.0.0.dist-info/entry_points.txt
mantarix_cli-1.0.0.dist-info/METADATA
mantarix_cli-1.0.0.dist-info/WHEEL
mantarix_cli-1.0.0.dist-info/RECORD
