Metadata-Version: 2.3
Name: mantarix-cli
Version: 1.0.0
Summary: Mantarix CLI
License: Apache-2.0
Author: Appveyor Systems Inc.
Author-email: hello@mantarix.dev
Requires-Python: >=3.8,<4.0
Classifier: License :: OSI Approved :: Apache Software License
Classifier: Programming Language :: Python :: 3
Classifier: Programming Language :: Python :: 3.8
Classifier: Programming Language :: Python :: 3.9
Classifier: Programming Language :: Python :: 3.10
Classifier: Programming Language :: Python :: 3.11
Classifier: Programming Language :: Python :: 3.12
Classifier: Programming Language :: Python :: 3.13
Requires-Dist: cookiecutter (>=2.6.0,<3.0.0)
Requires-Dist: mantarix (==1.0.0)
Requires-Dist: packaging
Requires-Dist: qrcode (>=7.4.2,<8.0.0)
Requires-Dist: toml (>=0.10.2,<0.11.0)
Requires-Dist: watchdog (>=4.0.0,<5.0.0)
Project-URL: repository, https://github.com/mantarix-dev/mantarix
